MANIFEST.in
README.txt
setup.cfg
setup.py
Solgema/__init__.py
Solgema/__init__.py~
Solgema.blinks.egg-info/PKG-INFO
Solgema.blinks.egg-info/PKG-INFO~
Solgema.blinks.egg-info/SOURCES.txt
Solgema.blinks.egg-info/dependency_links.txt
Solgema.blinks.egg-info/entry_points.txt
Solgema.blinks.egg-info/namespace_packages.txt
Solgema.blinks.egg-info/not-zip-safe
Solgema.blinks.egg-info/requires.txt
Solgema.blinks.egg-info/top_level.txt
Solgema/blinks/__init__.py
Solgema/blinks/config.py
Solgema/blinks/configure.zcml
Solgema/blinks/interfaces.py
Solgema/blinks/profiles.zcml
Solgema/blinks/setuphandlers.py
Solgema/blinks/Extensions/Install.py
Solgema/blinks/Extensions/Install.py~
Solgema/blinks/Extensions/__init__.py
Solgema/blinks/locales/Solgema.blinks.pot
Solgema/blinks/locales/en/LC_MESSAGES/Solgema.blinks.mo
Solgema/blinks/locales/en/LC_MESSAGES/Solgema.blinks.po
Solgema/blinks/locales/en/LC_MESSAGES/Solgema.blinks.po~
Solgema/blinks/locales/fr/LC_MESSAGES/Solgema.blinks.mo
Solgema/blinks/locales/fr/LC_MESSAGES/Solgema.blinks.po
Solgema/blinks/locales/fr/LC_MESSAGES/Solgema.blinks.po~
Solgema/blinks/portlets/__init__.py
Solgema/blinks/portlets/configure.zcml
Solgema/blinks/portlets/solgemablinks.pt
Solgema/blinks/portlets/solgemablinks.py
Solgema/blinks/profiles/default/browserlayer.xml
Solgema/blinks/profiles/default/cssregistry.xml
Solgema/blinks/profiles/default/metadata.xml
Solgema/blinks/profiles/default/portlets.xml
Solgema/blinks/profiles/default/skins.xml
Solgema/blinks/profiles/uninstall/cssregistry.xml
Solgema/blinks/profiles/uninstall/import_steps.xml
Solgema/blinks/profiles/uninstall/metadata.xml
Solgema/blinks/profiles/uninstall/skins.xml
Solgema/blinks/skins/__init__.py
Solgema/blinks/skins/solgemablinks/IE6Fixes.css.dtml~
Solgema/blinks/skins/solgemablinks/__init__.py
Solgema/blinks/skins/solgemablinks/accessibilite_icon.png.py~
Solgema/blinks/skins/solgemablinks/accessibilite_icon_hover.png.py~
Solgema/blinks/skins/solgemablinks/base_properties.props~
Solgema/blinks/skins/solgemablinks/configuration_icon.png.py~
Solgema/blinks/skins/solgemablinks/configuration_icon_hover.png.py~
Solgema/blinks/skins/solgemablinks/contact_icon.png.py~
Solgema/blinks/skins/solgemablinks/contact_icon_hover.png.py~
Solgema/blinks/skins/solgemablinks/footer_background.png.py~
